ppchain/__init__.py
ppchain/cli.py
ppchain/ppchain.py
ppchain-0.0.1.dist-info/AUTHORS.rst
ppchain-0.0.1.dist-info/LICENSE
ppchain-0.0.1.dist-info/METADATA
ppchain-0.0.1.dist-info/WHEEL
ppchain-0.0.1.dist-info/entry_points.txt
ppchain-0.0.1.dist-info/top_level.txt
ppchain-0.0.1.dist-info/RECORD
