Metadata-Version: 2.1
Name: ppchain
Version: 0.0.1
Summary: Your probabilistic modeling open source copilot
Home-page: https://github.com/shadowboxingskills/ppchain
Author: Marc Fournier-Carrie
Author-email: marc@valuegrid.io
License: MIT license
Keywords: ppchain
Classifier: Development Status :: 2 - Pre-Alpha
Classifier: Intended Audience :: Developers
Classifier: License :: OSI Approved :: MIT License
Classifier: Natural Language :: English
Classifier: Programming Language :: Python :: 3
Classifier: Programming Language :: Python :: 3.6
Classifier: Programming Language :: Python :: 3.7
Classifier: Programming Language :: Python :: 3.8
Requires-Python: >=3.6
License-File: LICENSE
License-File: AUTHORS.rst
